setup.py
slackmsg/__init__.py
slackmsg.egg-info/PKG-INFO
slackmsg.egg-info/SOURCES.txt
slackmsg.egg-info/dependency_links.txt
slackmsg.egg-info/entry_points.txt
slackmsg.egg-info/requires.txt
slackmsg.egg-info/top_level.txt